chemsmart/__init__.py
chemsmart/analysis/dias.py
chemsmart/analysis/thermochemistry.py
chemsmart/cli/__init__.py
chemsmart/cli/config.py
chemsmart/cli/job.py
chemsmart/cli/jobrunner.py
chemsmart/cli/logger.py
chemsmart/cli/main.py
chemsmart/cli/run.py
chemsmart/cli/sub.py
chemsmart/cli/subcommands.py
chemsmart/cli/update.py
chemsmart/cli/gaussian/__init__.py
chemsmart/cli/gaussian/com.py
chemsmart/cli/gaussian/crest.py
chemsmart/cli/gaussian/custom.py
chemsmart/cli/gaussian/dias.py
chemsmart/cli/gaussian/gaussian.py
chemsmart/cli/gaussian/irc.py
chemsmart/cli/gaussian/link.py
chemsmart/cli/gaussian/modred.py
chemsmart/cli/gaussian/nci.py
chemsmart/cli/gaussian/opt.py
chemsmart/cli/gaussian/qrc.py
chemsmart/cli/gaussian/resp.py
chemsmart/cli/gaussian/scan.py
chemsmart/cli/gaussian/singlepoint.py
chemsmart/cli/gaussian/tddft.py
chemsmart/cli/gaussian/traj.py
chemsmart/cli/gaussian/ts.py
chemsmart/cli/gaussian/wbi.py
chemsmart/cli/mol/__init__.py
chemsmart/cli/mol/align.py
chemsmart/cli/mol/irc.py
chemsmart/cli/mol/mo.py
chemsmart/cli/mol/mol.py
chemsmart/cli/mol/movie.py
chemsmart/cli/mol/nci.py
chemsmart/cli/mol/spin.py
chemsmart/cli/mol/visualize.py
chemsmart/cli/nciplot/__init__.py
chemsmart/cli/nciplot/nciplot.py
chemsmart/cli/orca/__init__.py
chemsmart/cli/orca/inp.py
chemsmart/cli/orca/irc.py
chemsmart/cli/orca/modred.py
chemsmart/cli/orca/opt.py
chemsmart/cli/orca/orca.py
chemsmart/cli/orca/qrc.py
chemsmart/cli/orca/scan.py
chemsmart/cli/orca/singlepoint.py
chemsmart/cli/orca/ts.py
chemsmart/cli/thermochemistry/__init__.py
chemsmart/cli/thermochemistry/boltzmann.py
chemsmart/cli/thermochemistry/thermochemistry.py
chemsmart/io/__init__.py
chemsmart/io/converter.py
chemsmart/io/file.py
chemsmart/io/folder.py
chemsmart/io/organizer.py
chemsmart/io/yaml.py
chemsmart/io/gaussian/__init__.py
chemsmart/io/gaussian/cube.py
chemsmart/io/gaussian/folder.py
chemsmart/io/gaussian/gengenecp.py
chemsmart/io/gaussian/input.py
chemsmart/io/gaussian/output.py
chemsmart-0.1.16.dist-info/LICENSE
chemsmart-0.1.16.dist-info/LICENSE.LESSER
chemsmart-0.1.16.dist-info/METADATA
chemsmart-0.1.16.dist-info/WHEEL
chemsmart-0.1.16.dist-info/top_level.txt
chemsmart-0.1.16.dist-info/RECORD
