Metadata-Version: 2.1
Name: chemsmart
Version: 0.1.16
Summary: CHEMSMART: Chemistry Simulation and Modeling Automation Toolkit
Author-email: xinglong-zhang <xinglong.zhang@cuhk.edu.hk>
License: GNU GENERAL PUBLIC LICENSE
Project-URL: homepage, https://github.com/xinglong-zhang/chemsmart/
Project-URL: Source, https://github.com/xinglong-zhang/chemsmart/
Classifier: Programming Language :: Python :: 3
Classifier: License :: OSI Approved :: MIT License
Classifier: Operating System :: OS Independent
Requires-Python: ~=3.10
License-File: LICENSE
License-File: LICENSE.LESSER
Requires-Dist: ase==3.24.0
Requires-Dist: basis-set-exchange==0.11
Requires-Dist: click==8.1.8
Requires-Dist: dictdiffer==0.9.0
Requires-Dist: filelock
Requires-Dist: joblib==1.4.2
Requires-Dist: networkx==3.4.2
Requires-Dist: numpy~=1.26.4
Requires-Dist: pytest==8.3.4
Requires-Dist: pyyaml
Requires-Dist: pymatgen==2025.1.24
Requires-Dist: rdkit==2025.3.3
Requires-Dist: tomlkit==0.13.2
Requires-Dist: types-PyYAML
Requires-Dist: scipy==1.15.2
Requires-Dist: pandas==2.2.3
Requires-Dist: openpyxl==3.1.5
Requires-Dist: requests>=2.32.3
Requires-Dist: tenacity>=9.1.2
Requires-Dist: matplotlib>=3.10.1
Requires-Dist: scikit-learn>=1.6.1
Requires-Dist: pytest-mock>=3.14.0
Requires-Dist: pyvoro>=1.3.2
Provides-Extra: dev
Requires-Dist: pre-commit>=3.6.0; extra == "dev"
Requires-Dist: flake8; extra == "dev"
Requires-Dist: ruff; extra == "dev"
Requires-Dist: black; extra == "dev"
Requires-Dist: isort; extra == "dev"
Requires-Dist: gitchangelog; extra == "dev"
Requires-Dist: pipreqs; extra == "dev"
Requires-Dist: types-PyYAML; extra == "dev"
Provides-Extra: docs
Requires-Dist: sphinx; extra == "docs"
Requires-Dist: myst-parser; extra == "docs"
Requires-Dist: sphinx-autodoc-typehints; extra == "docs"
Requires-Dist: sphinx-rtd-theme; extra == "docs"
Requires-Dist: doc8; extra == "docs"
Requires-Dist: rstcheck; extra == "docs"
Requires-Dist: rstfmt; extra == "docs"
Provides-Extra: test
Requires-Dist: pytest; extra == "test"
Requires-Dist: pytest-mock; extra == "test"
Requires-Dist: coverage; extra == "test"
Requires-Dist: pytest-cov; extra == "test"
